superclaude/__init__.py
superclaude/__version__.py
superclaude/pytest_plugin.py
superclaude/agents/README.md
superclaude/agents/__init__.py
superclaude/agents/backend-architect.md
superclaude/agents/business-panel-experts.md
superclaude/agents/deep-research-agent.md
superclaude/agents/deep-research.md
superclaude/agents/devops-architect.md
superclaude/agents/frontend-architect.md
superclaude/agents/learning-guide.md
superclaude/agents/performance-engineer.md
superclaude/agents/pm-agent.md
superclaude/agents/python-expert.md
superclaude/agents/quality-engineer.md
superclaude/agents/refactoring-expert.md
superclaude/agents/repo-index.md
superclaude/agents/requirements-analyst.md
superclaude/agents/root-cause-analyst.md
superclaude/agents/security-engineer.md
superclaude/agents/self-review.md
superclaude/agents/socratic-mentor.md
superclaude/agents/system-architect.md
superclaude/agents/technical-writer.md
superclaude/cli/__init__.py
superclaude/cli/doctor.py
superclaude/cli/install_commands.py
superclaude/cli/install_mcp.py
superclaude/cli/install_skill.py
superclaude/cli/main.py
superclaude/commands/README.md
superclaude/commands/__init__.py
superclaude/commands/agent.md
superclaude/commands/analyze.md
superclaude/commands/brainstorm.md
superclaude/commands/build.md
superclaude/commands/business-panel.md
superclaude/commands/cleanup.md
superclaude/commands/design.md
superclaude/commands/document.md
superclaude/commands/estimate.md
superclaude/commands/explain.md
superclaude/commands/git.md
superclaude/commands/help.md
superclaude/commands/implement.md
superclaude/commands/improve.md
superclaude/commands/index-repo.md
superclaude/commands/index.md
superclaude/commands/load.md
superclaude/commands/pm.md
superclaude/commands/recommend.md
superclaude/commands/reflect.md
superclaude/commands/research.md
superclaude/commands/save.md
superclaude/commands/sc.md
superclaude/commands/select-tool.md
superclaude/commands/spawn.md
superclaude/commands/spec-panel.md
superclaude-4.2.0.dist-info/METADATA
superclaude-4.2.0.dist-info/WHEEL
superclaude-4.2.0.dist-info/entry_points.txt
superclaude-4.2.0.dist-info/licenses/LICENSE
superclaude-4.2.0.dist-info/RECORD
