Metadata-Version: 2.4
Name: superclaude
Version: 4.2.0
Summary: AI-enhanced development framework for Claude Code - pytest plugin with optional skills
Project-URL: Homepage, https://github.com/SuperClaude-Org/SuperClaude_Framework
Project-URL: GitHub, https://github.com/SuperClaude-Org/SuperClaude_Framework
Project-URL: Bug Tracker, https://github.com/SuperClaude-Org/SuperClaude_Framework/issues
Project-URL: Documentation, https://github.com/SuperClaude-Org/SuperClaude_Framework/blob/main/README.md
Author: Kazuki Nakai
Author-email: NomenAK <anton.knoery@gmail.com>, Mithun Gowda B <mithungowda.b7411@gmail.com>
License: MIT
License-File: LICENSE
Keywords: ai,automation,claude,development,framework,plugin,pytest,testing
Classifier: Development Status :: 4 - Beta
Classifier: Environment :: Console
Classifier: Framework :: Pytest
Classifier: Intended Audience :: Developers
Classifier: License :: OSI Approved :: MIT License
Classifier: Operating System :: OS Independent
Classifier: Programming Language :: Python :: 3
Classifier: Programming Language :: Python :: 3.10
Classifier: Programming Language :: Python :: 3.11
Classifier: Programming Language :: Python :: 3.12
Classifier: Topic :: Scientific/Engineering :: Artificial Intelligence
Classifier: Topic :: Software Development :: Libraries :: Python Modules
Classifier: Topic :: Software Development :: Testing
Requires-Python: >=3.10
Requires-Dist: click>=8.0.0
Requires-Dist: pytest>=7.0.0
Requires-Dist: rich>=13.0.0
Provides-Extra: dev
Requires-Dist: black>=22.0; extra == 'dev'
Requires-Dist: mypy>=1.0; extra == 'dev'
Requires-Dist: pytest-benchmark>=4.0.0; extra == 'dev'
Requires-Dist: pytest-cov>=4.0.0; extra == 'dev'
Requires-Dist: ruff>=0.1.0; extra == 'dev'
Requires-Dist: scipy>=1.10.0; extra == 'dev'
Provides-Extra: test
Requires-Dist: pytest-cov>=4.0.0; extra == 'test'
Requires-Dist: pytest>=7.0.0; extra == 'test'
Requires-Dist: scipy>=1.10.0; extra == 'test'
